[
    {
        "nl_query": "which states border states through which the mississippi traverses ?",
        "sql_query": "SELECT border_info.border FROM border_info WHERE border_info.state_name IN(SELECT river.traverse FROM river WHERE river.river_name='mississippi');",
        "sql_query_result": {
            "header": [
                "border"
            ],
            "cell": [
                [
                    "missouri"
                ],
                [
                    "tennessee"
                ],
                [
                    "mississippi"
                ],
                [
                    "louisiana"
                ],
                [
                    "texas"
                ],
                [
                    "oklahoma"
                ],
                [
                    "wisconsin"
                ],
                [
                    "indiana"
                ],
                [
                    "kentucky"
                ],
                [
                    "iowa"
                ],
                [
                    "minnesota"
                ],
                [
                    "illinois"
                ],
                [
                    "nebraska"
                ],
                [
                    "south dakota"
                ],
                [
                    "ohio"
                ],
                [
                    "west virginia"
                ],
                [
                    "virginia"
                ],
                [
                    "arkansas"
                ],
                [
                    "north dakota"
                ],
                [
                    "alabama"
                ],
                [
                    "kansas"
                ],
                [
                    "north carolina"
                ],
                [
                    "georgia"
                ],
                [
                    "michigan"
                ]
            ]
        },
        "statement": "States border the states through which the Mississippi River traverses are Mississippi, Louisiana, Texas, Oklahoma, Wisconsin, Indiana, Kentucky, Iowa, Minnesota, Illinois, Nebraska, South dakota, Ohio, West virginia, Virginia, Arkansas, North dakota, Alabama, Kansas, North carolina, Georgia, and Michigan."
    },
    {
        "nl_query": "what are the cities in california",
        "sql_query": "SELECT city.city_name FROM city WHERE city.state_name='california';",
        "sql_query_result": {
            "header": [
                "city_name"
            ],
            "cell": [
                [
                    "los angeles"
                ],
                [
                    "san diego"
                ],
                [
                    "san francisco"
                ],
                [
                    "san jose"
                ],
                [
                    "long beach"
                ],
                [
                    "oakland"
                ],
                [
                    "sacramento"
                ],
                [
                    "anaheim"
                ],
                [
                    "fresno"
                ],
                [
                    "santa ana"
                ],
                [
                    "riverside"
                ],
                [
                    "huntington beach"
                ],
                [
                    "stockton"
                ],
                [
                    "glendale"
                ],
                [
                    "fremont"
                ],
                [
                    "torrance"
                ],
                [
                    "garden grove"
                ],
                [
                    "san bernardino"
                ],
                [
                    "pasadena"
                ],
                [
                    "east los angeles"
                ],
                [
                    "oxnard"
                ],
                [
                    "modesto"
                ],
                [
                    "sunnyvale"
                ],
                [
                    "bakersfield"
                ],
                [
                    "concord"
                ],
                [
                    "berkeley"
                ],
                [
                    "fullerton"
                ],
                [
                    "inglewood"
                ],
                [
                    "hayward"
                ],
                [
                    "pomona"
                ],
                [
                    "orange"
                ],
                [
                    "ontario"
                ],
                [
                    "santa monica"
                ],
                [
                    "santa clara"
                ],
                [
                    "citrus heights"
                ],
                [
                    "norwalk"
                ],
                [
                    "burbank"
                ],
                [
                    "chula vista"
                ],
                [
                    "santa rosa"
                ],
                [
                    "downey"
                ],
                [
                    "costa mesa"
                ],
                [
                    "compton"
                ],
                [
                    "carson"
                ],
                [
                    "salinas"
                ],
                [
                    "west covina"
                ],
                [
                    "vallejo"
                ],
                [
                    "el monte"
                ],
                [
                    "daly city"
                ],
                [
                    "thousand oaks"
                ],
                [
                    "san mateo"
                ],
                [
                    "simi valley"
                ],
                [
                    "oceanside"
                ],
                [
                    "richmond"
                ],
                [
                    "lakewood"
                ],
                [
                    "santa barbara"
                ],
                [
                    "el cajon"
                ],
                [
                    "ventura"
                ],
                [
                    "westminster"
                ],
                [
                    "whittier"
                ],
                [
                    "south gate"
                ],
                [
                    "alhambra"
                ],
                [
                    "buena park"
                ],
                [
                    "san leandro"
                ],
                [
                    "alameda"
                ],
                [
                    "newport beach"
                ],
                [
                    "escondido"
                ],
                [
                    "irvine"
                ],
                [
                    "mountain view"
                ],
                [
                    "fairfield"
                ],
                [
                    "redondo beach"
                ],
                [
                    "scotts valley"
                ]
            ]
        },
        "statement": "Cities in California are Los angeles, San diego, San francisco, San jose, Long beach, Oakland, Sacramento, Anaheim, Fresno, Santa ana, Riverside, Huntington beach, Stockton, Glendale, Fremont, Torrance, Garden grove, San bernardino, Pasadena, East los angeles, Oxnard, Modesto, Sunnyvale, Bakersfield, Concord, Berkeley, Fullerton, Inglewood, Hayward, Pomona, Orange, Ontario, Santa monica, Santa clara, Citrus heights, Norwalk, Burbank, Chula vista, Santa rosa, Downey, Costa mesa, Compton, Carson, Salinas, West covina, Vallejo, El monte, Daly city, Thousand oaks, San mateo, Simi valley, Oceanside, Richmond, Lakewood, Santa barbara, El cajon, Ventura, Westminster, Whittier, South gate, Alhambra, Buena park, San leandro, Alameda, Newport beach, Escondido, Irvine, Mountain view, Fairfield, Redondo beach, and Scotts valley."
    },
    {
        "nl_query": "what are the major cities of the united states",
        "sql_query": "SELECT city.city_name FROM city WHERE city.population>150000;",
        "sql_query_result": {
            "header": [
                "city_name"
            ],
            "cell": [
                [
                    "birmingham"
                ],
                [
                    "mobile"
                ],
                [
                    "montgomery"
                ],
                [
                    "anchorage"
                ],
                [
                    "phoenix"
                ],
                [
                    "tucson"
                ],
                [
                    "mesa"
                ],
                [
                    "little rock"
                ],
                [
                    "los angeles"
                ],
                [
                    "san diego"
                ],
                [
                    "san francisco"
                ],
                [
                    "san jose"
                ],
                [
                    "long beach"
                ],
                [
                    "oakland"
                ],
                [
                    "sacramento"
                ],
                [
                    "anaheim"
                ],
                [
                    "fresno"
                ],
                [
                    "santa ana"
                ],
                [
                    "riverside"
                ],
                [
                    "huntington beach"
                ],
                [
                    "denver"
                ],
                [
                    "colorado springs"
                ],
                [
                    "aurora"
                ],
                [
                    "washington"
                ],
                [
                    "jacksonville"
                ],
                [
                    "miami"
                ],
                [
                    "tampa"
                ],
                [
                    "st. petersburg"
                ],
                [
                    "fort lauderdale"
                ],
                [
                    "atlanta"
                ],
                [
                    "columbus"
                ],
                [
                    "honolulu"
                ],
                [
                    "ewa"
                ],
                [
                    "chicago"
                ],
                [
                    "indianapolis"
                ],
                [
                    "fort wayne"
                ],
                [
                    "gary"
                ],
                [
                    "des moines"
                ],
                [
                    "wichita"
                ],
                [
                    "kansas city"
                ],
                [
                    "louisville"
                ],
                [
                    "lexington"
                ],
                [
                    "new orleans"
                ],
                [
                    "baton rouge"
                ],
                [
                    "shreveport"
                ],
                [
                    "metairie"
                ],
                [
                    "baltimore"
                ],
                [
                    "boston"
                ],
                [
                    "worcester"
                ],
                [
                    "springfield"
                ],
                [
                    "detroit"
                ],
                [
                    "grand rapids"
                ],
                [
                    "warren"
                ],
                [
                    "flint"
                ],
                [
                    "minneapolis"
                ],
                [
                    "st. paul"
                ],
                [
                    "jackson"
                ],
                [
                    "st. louis"
                ],
                [
                    "omaha"
                ],
                [
                    "lincoln"
                ],
                [
                    "las vegas"
                ],
                [
                    "newark"
                ],
                [
                    "jersey city"
                ],
                [
                    "albuquerque"
                ],
                [
                    "new york"
                ],
                [
                    "buffalo"
                ],
                [
                    "rochester"
                ],
                [
                    "yonkers"
                ],
                [
                    "syracuse"
                ],
                [
                    "charlotte"
                ],
                [
                    "greensboro"
                ],
                [
                    "cleveland"
                ],
                [
                    "cincinnati"
                ],
                [
                    "toledo"
                ],
                [
                    "akron"
                ],
                [
                    "dayton"
                ],
                [
                    "oklahoma city"
                ],
                [
                    "tulsa"
                ],
                [
                    "portland"
                ],
                [
                    "philadelphia"
                ],
                [
                    "pittsburgh"
                ],
                [
                    "providence"
                ],
                [
                    "memphis"
                ],
                [
                    "nashville"
                ],
                [
                    "knoxville"
                ],
                [
                    "chattanooga"
                ],
                [
                    "houston"
                ],
                [
                    "dallas"
                ],
                [
                    "san antonio"
                ],
                [
                    "el paso"
                ],
                [
                    "fort worth"
                ],
                [
                    "austin"
                ],
                [
                    "corpus christi"
                ],
                [
                    "lubbock"
                ],
                [
                    "arlington"
                ],
                [
                    "salt lake city"
                ],
                [
                    "norfolk"
                ],
                [
                    "virginia beach"
                ],
                [
                    "richmond"
                ],
                [
                    "seattle"
                ],
                [
                    "spokane"
                ],
                [
                    "tacoma"
                ],
                [
                    "milwaukee"
                ],
                [
                    "madison"
                ]
            ]
        },
        "statement": "The major cities in the United States are Birmingham, Mobile, Montgomery, Anchorage, Phoenix, Tucson, Mesa, Little rock, Los angeles, San diego, San francisco, San jose, Long beach, Oakland, Sacramento, Anaheim, Fresno, Santa ana, Riverside, Huntington beach, Denver, Colorado springs, Aurora, Washington, Jacksonville, Miami, Tampa, St. petersburg, Fort lauderdale, Atlanta, Columbus, Honolulu, Ewa, Chicago, Indianapolis, Fort wayne, Gary, Des moines, Wichita, Kansas city, Louisville, Lexington, New orleans, Baton rouge, Shreveport, Metairie, Baltimore, Boston, Worcester, Springfield, Detroit, Grand rapids, Warren, Flint, Minneapolis, St. paul, Jackson, St. louis, Omaha, Lincoln, Las vegas, Newark, Jersey city, Albuquerque, New york, Buffalo, Rochester, Yonkers, Syracuse, Charlotte, Greensboro, Cleveland, Cincinnati, Toledo, Akron, Dayton, Oklahoma city, Tulsa, Portland, Philadelphia, Pittsburgh, Providence, Memphis, Nashville, Knoxville, Chattanooga, Houston, Dallas, San antonio, El paso, Fort worth, Austin, Corpus christi, Lubbock, Arlington, Salt lake city, Norfolk, Virginia beach, Richmond, Seattle, Spokane, Tacoma, Milwaukee, Madison."
    },
    {
        "nl_query": "what rivers do not run through tennessee",
        "sql_query": "SELECT river.river_name FROM river WHERE river.river_name NOT IN(SELECT river.river_name FROM river WHERE river.traverse='tennessee');",
        "sql_query_result": {
            "header": [
                "river_name"
            ],
            "cell": [
                [
                    "missouri"
                ],
                [
                    "colorado"
                ],
                [
                    "ohio"
                ],
                [
                    "red"
                ],
                [
                    "arkansas"
                ],
                [
                    "canadian"
                ],
                [
                    "connecticut"
                ],
                [
                    "delaware"
                ],
                [
                    "little missouri"
                ],
                [
                    "snake"
                ],
                [
                    "chattahoochee"
                ],
                [
                    "cimarron"
                ],
                [
                    "green"
                ],
                [
                    "north platte"
                ],
                [
                    "potomac"
                ],
                [
                    "republican"
                ],
                [
                    "rio grande"
                ],
                [
                    "san juan"
                ],
                [
                    "wabash"
                ],
                [
                    "yellowstone"
                ],
                [
                    "allegheny"
                ],
                [
                    "bighorn"
                ],
                [
                    "cheyenne"
                ],
                [
                    "clark fork"
                ],
                [
                    "columbia"
                ],
                [
                    "dakota"
                ],
                [
                    "gila"
                ],
                [
                    "hudson"
                ],
                [
                    "neosho"
                ],
                [
                    "niobrara"
                ],
                [
                    "ouachita"
                ],
                [
                    "pearl"
                ],
                [
                    "pecos"
                ],
                [
                    "powder"
                ],
                [
                    "roanoke"
                ],
                [
                    "rock"
                ],
                [
                    "smoky hill"
                ],
                [
                    "south platte"
                ],
                [
                    "st. francis"
                ],
                [
                    "tombigbee"
                ],
                [
                    "washita"
                ],
                [
                    "wateree catawba"
                ],
                [
                    "white"
                ]
            ]
        },
        "statement": "Rivers do not run through Tennesse are Missouri, Colorado, Ohio, Red, Arkansas, Canadian, Connecticut, Delaware, Little missouri, Snake, Chattahoochee, Cimarron, Green, North platte, Potomac, Republican, Rio grande, San juan, Wabash, Yellowstone, Allegheny, Bighorn, Cheyenne, Clark fork, Columbia, Dakota, Gila, Hudson, Neosho, Niobrara, Ouachita, Pearl, Pecos, Powder, Roanoke, Rock, Smoky hill, South platte, St. francis, Tombigbee, Washita, Wateree catawba, and White."
    }
]